README.md
setup.py
kartoshechka/__init__.py
kartoshechka/exceptions.py
kartoshechka/loader.py
kartoshechka/transformers.py
kartoshechka.egg-info/PKG-INFO
kartoshechka.egg-info/SOURCES.txt
kartoshechka.egg-info/dependency_links.txt
kartoshechka.egg-info/top_level.txt
kartoshechka.egg-info/zip-safe